{
  "ticker": "2613",
  "schemaVersion": 2,
  "updatedAt": "2026-04-23T20:21:41Z",
  "unit": "Million NTD; margin rows are percent; EPS is TWD per share",
  "industryType": "general",
  "sector": "Industrials",
  "industry": "Marine Shipping",
  "marketCap": 3171,
  "enterpriseValue": 7968,
  "yahooSuffix": ".TW",
  "valuation": {
    "P/E (TTM)": 20.26,
    "Forward P/E": null,
    "P/S (TTM)": 0.94,
    "P/B": 0.96,
    "EV/EBITDA": 14.86,
    "ROE": 4.87,
    "Beta": 0.49,
    "Debt/Equity": 168.13
  },
  "annual": {
    "periods": [
      "2018-12-31",
      "2019-12-31",
      "2020-12-31",
      "2021-12-31",
      "2022-12-31",
      "2023-12-31",
      "2024-12-31",
      "2025-12-31"
    ],
    "series": {
      "Revenue": [
        2850.91,
        2878.82,
        2830.49,
        3084.14,
        3152.627,
        3148.316,
        3285.815,
        3367.572
      ],
      "Cost of Revenue": [
        2601.13,
        2542.63,
        2503.4,
        2538.07,
        2617.066,
        2680.592,
        2735.427,
        2796.196
      ],
      "Gross Profit": [
        249.78,
        336.19,
        327.1,
        546.07,
        535.561,
        467.724,
        550.388,
        571.376
      ],
      "Gross Margin (%)": [
        8.761413022508604,
        11.678048644930907,
        11.556302972276887,
        17.70574617235275,
        16.987769247678205,
        14.856323189921214,
        16.750425693473307,
        16.96700174487732
      ],
      "Selling & Marketing Exp": [
        124.35,
        130.23,
        140.37,
        150.36,
        89.107,
        104.258,
        101.763,
        112.414
      ],
      "R&D Exp": [
        null,
        null,
        null,
        null,
        0.0,
        0.0,
        0.0,
        0.0
      ],
      "General & Admin Exp": [
        141.28,
        150.51,
        149.29,
        194.24,
        101.565,
        94.341,
        107.532,
        108.073
      ],
      "Operating Income": [
        108.51,
        185.68,
        177.81,
        351.83,
        344.889,
        269.125,
        341.093,
        350.889
      ],
      "Operating Margin (%)": [
        3.806153123037907,
        6.449864875191919,
        6.281951181597534,
        11.40771819696901,
        10.939733752200942,
        8.548220699573994,
        10.380773111085073,
        10.41964358891213
      ],
      "Net Income": [
        58.47,
        35.38,
        30.75,
        222.49,
        143.517,
        97.653,
        115.553,
        157.092
      ],
      "Net Margin (%)": [
        2.050924090904308,
        1.2289757609020362,
        1.0863843362809975,
        7.214004552322528,
        4.55229876544228,
        3.10175344533395,
        3.5167226395886564,
        4.6648445823875475
      ],
      "EPS": [
        0.53,
        0.27,
        0.23,
        1.63,
        1.05,
        0.71,
        0.84,
        1.14
      ],
      "Op Cash Flow": [
        256.9,
        557.29,
        726.53,
        746.72,
        916.683,
        772.914,
        837.346,
        878.648
      ],
      "Investing Cash Flow": [
        -403.08,
        -298.56,
        -4.7,
        -128.98,
        -210.413,
        -339.413,
        -8.356,
        -1059.114
      ],
      "Financing Cash Flow": [
        141.74,
        -164.6,
        -567.5,
        -548.47,
        -650.035,
        -399.046,
        -783.87,
        145.721
      ],
      "CAPEX": [
        -896.29,
        -896.29,
        -386.6,
        -253.84,
        -245.202,
        -337.845,
        -74.81,
        -1044.445
      ]
    }
  },
  "quarterly": {
    "periods": [
      "2018-03-31",
      "2018-06-30",
      "2018-09-30",
      "2018-12-31",
      "2019-03-31",
      "2019-06-30",
      "2019-09-30",
      "2019-12-31",
      "2020-03-31",
      "2020-06-30",
      "2020-09-30",
      "2020-12-31",
      "2021-03-31",
      "2021-06-30",
      "2021-09-30",
      "2021-12-31",
      "2022-03-31",
      "2022-06-30",
      "2022-09-30",
      "2022-12-31",
      "2023-03-31",
      "2023-06-30",
      "2023-09-30",
      "2023-12-31",
      "2024-03-31",
      "2024-06-30",
      "2024-09-30",
      "2024-12-31",
      "2025-03-31",
      "2025-06-30",
      "2025-09-30",
      "2025-12-31"
    ],
    "series": {
      "Revenue": [
        668.26,
        733.84,
        742.05,
        706.76,
        654.87,
        723.36,
        744.13,
        756.46,
        661.59,
        699.2,
        746.87,
        722.83,
        718.47,
        772.8,
        796.76,
        796.11,
        779.65,
        834.81,
        791.58,
        746.59,
        714.87,
        781.18,
        826.96,
        825.31,
        768.71,
        834.08,
        849.13,
        833.9,
        771.69,
        869.61,
        877.39,
        848.88
      ],
      "Cost of Revenue": [
        628.9,
        644.97,
        668.83,
        658.43,
        605.66,
        636.91,
        646.16,
        653.9,
        609.79,
        624.88,
        644.65,
        624.08,
        635.99,
        634.92,
        640.68,
        626.48,
        661.71,
        655.47,
        656.59,
        643.3,
        641.64,
        668.11,
        693.25,
        677.59,
        659.83,
        689.92,
        695.8,
        689.88,
        656.97,
        712.43,
        717.42,
        709.38
      ],
      "Gross Profit": [
        39.37,
        88.86,
        73.22,
        48.33,
        49.2,
        86.46,
        97.98,
        102.55,
        51.8,
        74.32,
        102.23,
        98.75,
        82.48,
        137.88,
        156.08,
        169.63,
        117.94,
        179.35,
        134.97,
        103.3,
        73.23,
        113.07,
        133.71,
        147.71,
        108.88,
        144.16,
        153.34,
        144.01,
        114.72,
        157.18,
        159.97,
        139.51
      ],
      "Gross Margin (%)": [
        5.891419507377368,
        12.108906573640029,
        9.867259618624082,
        6.83824777859528,
        7.5129414998396635,
        11.952554744525546,
        13.167054143765203,
        13.556566110567644,
        7.8296225759155975,
        10.62929061784897,
        13.687790378512995,
        13.661580177911818,
        11.479950450262363,
        17.841614906832298,
        19.589336814097095,
        21.307357023526897,
        15.127300711857886,
        21.483930475197948,
        17.05070870916395,
        13.836242114145648,
        10.243820554786186,
        14.47425689341765,
        16.168859436973978,
        17.897517296531003,
        14.163989020566921,
        17.283713792441972,
        18.058483388880383,
        17.26945676939681,
        14.86607316409439,
        18.074769149388807,
        18.23248498387262,
        16.434596173781923
      ],
      "Selling & Marketing Exp": [
        17.429,
        16.47,
        19.977,
        70.474,
        17.76,
        17.743,
        20.246,
        74.485,
        17.487,
        22.631,
        20.294,
        79.954,
        20.748,
        19.633,
        23.011,
        86.97,
        22.872,
        21.21,
        23.029,
        22.0,
        24.944,
        25.498,
        27.669,
        26.15,
        24.375,
        25.128,
        26.922,
        25.338,
        27.667,
        28.187,
        29.939,
        26.621
      ],
      "R&D Exp": [
        null,
        null,
        null,
        null,
        null,
        null,
        null,
        null,
        null,
        null,
        null,
        null,
        null,
        null,
        null,
        null,
        null,
        null,
        null,
        null,
        null,
        null,
        null,
        null,
        null,
        null,
        null,
        0.0,
        0.0,
        0.0,
        0.0,
        0.0
      ],
      "General & Admin Exp": [
        32.42,
        35.24,
        38.59,
        35.03,
        36.57,
        33.7,
        38.67,
        41.57,
        33.61,
        39.07,
        38.3,
        38.31,
        44.07,
        46.21,
        49.38,
        54.58,
        50.11,
        51.76,
        46.99,
        41.76,
        47.82,
        45.3,
        53.23,
        52.25,
        48.58,
        52.49,
        57.0,
        51.24,
        52.34,
        54.82,
        58.54,
        55.06
      ],
      "Operating Income": [
        6.95,
        53.63,
        34.61,
        13.32,
        12.63,
        52.76,
        59.31,
        60.98,
        18.2,
        35.24,
        63.92,
        60.45,
        38.41,
        91.67,
        106.7,
        115.05,
        67.83,
        127.58,
        87.99,
        61.54,
        25.41,
        67.77,
        80.48,
        95.46,
        60.3,
        91.67,
        96.34,
        92.76,
        62.39,
        102.35,
        101.43,
        84.45
      ],
      "Operating Margin (%)": [
        1.0400143656660583,
        7.308132562956502,
        4.664106192305101,
        1.8846567434489785,
        1.9286270557515233,
        7.293740322937403,
        7.9703815193581775,
        8.061232583348756,
        2.7509484726189934,
        5.040045766590389,
        8.558383654451243,
        8.362962245617918,
        5.3460826478489,
        11.862060041407869,
        13.39173653295848,
        14.45152051852131,
        8.700057718206889,
        15.28251937566632,
        11.115743197150001,
        8.242810645735945,
        3.5544924251961896,
        8.675337310222995,
        9.732030569797814,
        11.566562867286232,
        7.844310598275031,
        10.990552464991367,
        11.34573033575542,
        11.123635927569255,
        8.084852725835503,
        11.769643863341036,
        11.560423528875416,
        9.948402601074358
      ],
      "Net Income": [
        -3.13,
        38.37,
        19.6,
        3.63,
        -23.28,
        14.25,
        22.91,
        21.5,
        -16.76,
        -12.06,
        33.83,
        25.74,
        3.97,
        50.51,
        60.95,
        107.06,
        28.79,
        68.56,
        20.65,
        25.52,
        -31.03,
        39.74,
        38.74,
        50.2,
        20.58,
        46.52,
        49.26,
        -0.81,
        31.97,
        35.49,
        49.14,
        40.49
      ],
      "Net Margin (%)": [
        -0.4683805704366563,
        5.228660198408372,
        2.6413314466680147,
        0.5136114098137982,
        -3.5549040267534013,
        1.9699734571997345,
        3.078763119347426,
        2.8421859714988233,
        -2.5332910110491396,
        -1.7248283752860412,
        4.529570072435631,
        3.5610032787792423,
        0.5525630854454605,
        6.5359730848861295,
        7.649731412219489,
        13.447890366909096,
        3.6926826139934588,
        8.212647189180773,
        2.6087066373581944,
        3.4182081195837073,
        -4.340649348832655,
        5.087175810952662,
        4.684628035213311,
        6.082562915752869,
        2.6772124728441153,
        5.577402647228084,
        5.801231849069047,
        -0.09713394891473798,
        4.14285529163265,
        4.081139821299203,
        5.600702082312313,
        4.769814343605693
      ],
      "EPS": [
        -0.03,
        0.35,
        0.18,
        0.03,
        -0.19,
        0.12,
        0.18,
        0.16,
        -0.12,
        -0.09,
        0.25,
        0.19,
        0.03,
        0.37,
        0.45,
        0.78,
        0.21,
        0.5,
        0.15,
        0.19,
        -0.23,
        0.29,
        0.29,
        0.36,
        0.15,
        0.34,
        0.36,
        -0.01,
        0.23,
        0.26,
        0.36,
        0.29
      ],
      "Op Cash Flow": [
        -3.99,
        15.45,
        114.72,
        130.72,
        51.51,
        102.08,
        202.2,
        201.5,
        110.24,
        186.09,
        161.46,
        268.74,
        125.72,
        189.85,
        127.22,
        303.93,
        181.74,
        213.57,
        241.54,
        279.83,
        140.29,
        160.49,
        198.88,
        273.25,
        160.22,
        208.34,
        247.41,
        221.38,
        234.08,
        191.18,
        220.75,
        232.64
      ],
      "Investing Cash Flow": [
        -18.14,
        -203.46,
        -82.6,
        -98.88,
        -126.69,
        -40.82,
        -21.99,
        -109.06,
        -18.71,
        -78.34,
        -134.8,
        227.15,
        26.06,
        -5.51,
        -96.07,
        -53.46,
        -7.92,
        -100.55,
        -47.38,
        -54.56,
        -20.73,
        -225.63,
        -72.47,
        -20.58,
        -81.38,
        -20.46,
        -0.66,
        94.14,
        -137.91,
        -212.06,
        -75.76,
        -633.38
      ],
      "Financing Cash Flow": [
        34.51,
        137.86,
        6.56,
        -37.19,
        163.87,
        11.72,
        -192.25,
        -147.94,
        -118.96,
        -126.56,
        8.27,
        -330.25,
        -157.42,
        -185.54,
        -24.84,
        -180.67,
        -41.58,
        -245.41,
        -189.42,
        -173.62,
        -108.45,
        -7.73,
        -113.82,
        -169.05,
        -151.75,
        -211.37,
        -180.33,
        -240.42,
        -110.16,
        -80.26,
        -102.44,
        438.58
      ],
      "CAPEX": [
        -52.853,
        -99.925,
        -346.961,
        -396.549,
        -52.853,
        -99.925,
        -346.961,
        -396.549,
        -51.818,
        -96.199,
        -115.566,
        -123.014,
        -16.344,
        -51.516,
        -65.155,
        -120.83,
        -13.136,
        -46.027,
        -65.848,
        -127.852,
        -19.797,
        -117.278,
        -118.504,
        -160.791,
        -19.797,
        -117.278,
        -118.504,
        -160.791,
        -23.185,
        -38.18,
        -60.527,
        -445.145
      ]
    }
  },
  "quarterlyCore": {
    "periods": [
      "2018-03-31",
      "2018-06-30",
      "2018-09-30",
      "2018-12-31",
      "2019-03-31",
      "2019-06-30",
      "2019-09-30",
      "2019-12-31",
      "2020-03-31",
      "2020-06-30",
      "2020-09-30",
      "2020-12-31",
      "2021-03-31",
      "2021-06-30",
      "2021-09-30",
      "2021-12-31",
      "2022-03-31",
      "2022-06-30",
      "2022-09-30",
      "2022-12-31",
      "2023-03-31",
      "2023-06-30",
      "2023-09-30",
      "2023-12-31",
      "2024-03-31",
      "2024-06-30",
      "2024-09-30",
      "2024-12-31",
      "2025-03-31",
      "2025-06-30",
      "2025-09-30",
      "2025-12-31"
    ],
    "series": {
      "Revenue": [
        668.26,
        733.84,
        742.05,
        706.76,
        654.87,
        723.36,
        744.13,
        756.46,
        661.59,
        699.2,
        746.87,
        722.83,
        718.47,
        772.8,
        796.76,
        796.11,
        779.65,
        834.81,
        791.58,
        746.59,
        714.87,
        781.18,
        826.96,
        825.31,
        768.71,
        834.08,
        849.13,
        833.9,
        771.69,
        869.61,
        877.39,
        848.88
      ],
      "Cost of Revenue": [
        628.9,
        644.97,
        668.83,
        658.43,
        605.66,
        636.91,
        646.16,
        653.9,
        609.79,
        624.88,
        644.65,
        624.08,
        635.99,
        634.92,
        640.68,
        626.48,
        661.71,
        655.47,
        656.59,
        643.3,
        641.64,
        668.11,
        693.25,
        677.59,
        659.83,
        689.92,
        695.8,
        689.88,
        656.97,
        712.43,
        717.42,
        709.38
      ],
      "Gross Profit": [
        39.37,
        88.86,
        73.22,
        48.33,
        49.2,
        86.46,
        97.98,
        102.55,
        51.8,
        74.32,
        102.23,
        98.75,
        82.48,
        137.88,
        156.08,
        169.63,
        117.94,
        179.35,
        134.97,
        103.3,
        73.23,
        113.07,
        133.71,
        147.71,
        108.88,
        144.16,
        153.34,
        144.01,
        114.72,
        157.18,
        159.97,
        139.51
      ],
      "Gross Margin (%)": [
        5.891419507377368,
        12.108906573640029,
        9.867259618624082,
        6.83824777859528,
        7.5129414998396635,
        11.952554744525546,
        13.167054143765203,
        13.556566110567644,
        7.8296225759155975,
        10.62929061784897,
        13.687790378512995,
        13.661580177911818,
        11.479950450262363,
        17.841614906832298,
        19.589336814097095,
        21.307357023526897,
        15.127300711857886,
        21.483930475197948,
        17.05070870916395,
        13.836242114145648,
        10.243820554786186,
        14.47425689341765,
        16.168859436973978,
        17.897517296531003,
        14.163989020566921,
        17.283713792441972,
        18.058483388880383,
        17.26945676939681,
        14.86607316409439,
        18.074769149388807,
        18.23248498387262,
        16.434596173781923
      ],
      "Selling & Marketing Exp": [
        17.429,
        16.47,
        19.977,
        70.474,
        17.76,
        17.743,
        20.246,
        74.485,
        17.487,
        22.631,
        20.294,
        79.954,
        20.748,
        19.633,
        23.011,
        86.97,
        22.872,
        21.21,
        23.029,
        22.0,
        24.944,
        25.498,
        27.669,
        26.15,
        24.375,
        25.128,
        26.922,
        25.338,
        27.667,
        28.187,
        29.939,
        26.621
      ],
      "R&D Exp": [
        null,
        null,
        null,
        null,
        null,
        null,
        null,
        null,
        null,
        null,
        null,
        null,
        null,
        null,
        null,
        null,
        null,
        null,
        null,
        null,
        null,
        null,
        null,
        null,
        null,
        null,
        null,
        0.0,
        0.0,
        0.0,
        0.0,
        0.0
      ],
      "General & Admin Exp": [
        32.42,
        35.24,
        38.59,
        35.03,
        36.57,
        33.7,
        38.67,
        41.57,
        33.61,
        39.07,
        38.3,
        38.31,
        44.07,
        46.21,
        49.38,
        54.58,
        50.11,
        51.76,
        46.99,
        41.76,
        47.82,
        45.3,
        53.23,
        52.25,
        48.58,
        52.49,
        57.0,
        51.24,
        52.34,
        54.82,
        58.54,
        55.06
      ],
      "Operating Income": [
        6.95,
        53.63,
        34.61,
        13.32,
        12.63,
        52.76,
        59.31,
        60.98,
        18.2,
        35.24,
        63.92,
        60.45,
        38.41,
        91.67,
        106.7,
        115.05,
        67.83,
        127.58,
        87.99,
        61.54,
        25.41,
        67.77,
        80.48,
        95.46,
        60.3,
        91.67,
        96.34,
        92.76,
        62.39,
        102.35,
        101.43,
        84.45
      ],
      "Operating Margin (%)": [
        1.0400143656660583,
        7.308132562956502,
        4.664106192305101,
        1.8846567434489785,
        1.9286270557515233,
        7.293740322937403,
        7.9703815193581775,
        8.061232583348756,
        2.7509484726189934,
        5.040045766590389,
        8.558383654451243,
        8.362962245617918,
        5.3460826478489,
        11.862060041407869,
        13.39173653295848,
        14.45152051852131,
        8.700057718206889,
        15.28251937566632,
        11.115743197150001,
        8.242810645735945,
        3.5544924251961896,
        8.675337310222995,
        9.732030569797814,
        11.566562867286232,
        7.844310598275031,
        10.990552464991367,
        11.34573033575542,
        11.123635927569255,
        8.084852725835503,
        11.769643863341036,
        11.560423528875416,
        9.948402601074358
      ],
      "Net Income": [
        -3.13,
        38.37,
        19.6,
        3.63,
        -23.28,
        14.25,
        22.91,
        21.5,
        -16.76,
        -12.06,
        33.83,
        25.74,
        3.97,
        50.51,
        60.95,
        107.06,
        28.79,
        68.56,
        20.65,
        25.52,
        -31.03,
        39.74,
        38.74,
        50.2,
        20.58,
        46.52,
        49.26,
        -0.81,
        31.97,
        35.49,
        49.14,
        40.49
      ],
      "Net Margin (%)": [
        -0.4683805704366563,
        5.228660198408372,
        2.6413314466680147,
        0.5136114098137982,
        -3.5549040267534013,
        1.9699734571997345,
        3.078763119347426,
        2.8421859714988233,
        -2.5332910110491396,
        -1.7248283752860412,
        4.529570072435631,
        3.5610032787792423,
        0.5525630854454605,
        6.5359730848861295,
        7.649731412219489,
        13.447890366909096,
        3.6926826139934588,
        8.212647189180773,
        2.6087066373581944,
        3.4182081195837073,
        -4.340649348832655,
        5.087175810952662,
        4.684628035213311,
        6.082562915752869,
        2.6772124728441153,
        5.577402647228084,
        5.801231849069047,
        -0.09713394891473798,
        4.14285529163265,
        4.081139821299203,
        5.600702082312313,
        4.769814343605693
      ],
      "EPS": [
        -0.03,
        0.35,
        0.18,
        0.03,
        -0.19,
        0.12,
        0.18,
        0.16,
        -0.12,
        -0.09,
        0.25,
        0.19,
        0.03,
        0.37,
        0.45,
        0.78,
        0.21,
        0.5,
        0.15,
        0.19,
        -0.23,
        0.29,
        0.29,
        0.36,
        0.15,
        0.34,
        0.36,
        -0.01,
        0.23,
        0.26,
        0.36,
        0.29
      ],
      "Op Cash Flow": [
        -3.99,
        15.45,
        114.72,
        130.72,
        51.51,
        102.08,
        202.2,
        201.5,
        110.24,
        186.09,
        161.46,
        268.74,
        125.72,
        189.85,
        127.22,
        303.93,
        181.74,
        213.57,
        241.54,
        279.83,
        140.29,
        160.49,
        198.88,
        273.25,
        160.22,
        208.34,
        247.41,
        221.38,
        234.08,
        191.18,
        220.75,
        232.64
      ],
      "Investing Cash Flow": [
        -18.14,
        -203.46,
        -82.6,
        -98.88,
        -126.69,
        -40.82,
        -21.99,
        -109.06,
        -18.71,
        -78.34,
        -134.8,
        227.15,
        26.06,
        -5.51,
        -96.07,
        -53.46,
        -7.92,
        -100.55,
        -47.38,
        -54.56,
        -20.73,
        -225.63,
        -72.47,
        -20.58,
        -81.38,
        -20.46,
        -0.66,
        94.14,
        -137.91,
        -212.06,
        -75.76,
        -633.38
      ],
      "Financing Cash Flow": [
        34.51,
        137.86,
        6.56,
        -37.19,
        163.87,
        11.72,
        -192.25,
        -147.94,
        -118.96,
        -126.56,
        8.27,
        -330.25,
        -157.42,
        -185.54,
        -24.84,
        -180.67,
        -41.58,
        -245.41,
        -189.42,
        -173.62,
        -108.45,
        -7.73,
        -113.82,
        -169.05,
        -151.75,
        -211.37,
        -180.33,
        -240.42,
        -110.16,
        -80.26,
        -102.44,
        438.58
      ],
      "CAPEX": [
        -52.853,
        -99.925,
        -346.961,
        -396.549,
        -52.853,
        -99.925,
        -346.961,
        -396.549,
        -51.818,
        -96.199,
        -115.566,
        -123.014,
        -16.344,
        -51.516,
        -65.155,
        -120.83,
        -13.136,
        -46.027,
        -65.848,
        -127.852,
        -19.797,
        -117.278,
        -118.504,
        -160.791,
        -19.797,
        -117.278,
        -118.504,
        -160.791,
        -23.185,
        -38.18,
        -60.527,
        -445.145
      ]
    }
  },
  "quarterlyYtd": {
    "periods": [
      "2018-03-31",
      "2018-06-30",
      "2018-09-30",
      "2018-12-31",
      "2019-03-31",
      "2019-06-30",
      "2019-09-30",
      "2019-12-31",
      "2020-03-31",
      "2020-06-30",
      "2020-09-30",
      "2020-12-31",
      "2021-03-31",
      "2021-06-30",
      "2021-09-30",
      "2021-12-31",
      "2022-03-31",
      "2022-06-30",
      "2022-09-30",
      "2022-12-31",
      "2023-03-31",
      "2023-06-30",
      "2023-09-30",
      "2023-12-31",
      "2024-03-31",
      "2024-06-30",
      "2024-09-30",
      "2024-12-31",
      "2025-03-31",
      "2025-06-30",
      "2025-09-30",
      "2025-12-31"
    ],
    "series": {
      "Revenue": [
        668.26,
        1402.1,
        2144.1499999999996,
        2850.91,
        654.87,
        1378.23,
        2122.36,
        2878.82,
        661.59,
        1360.79,
        2107.66,
        2830.49,
        718.47,
        1491.27,
        2288.0299999999997,
        3084.14,
        779.65,
        1614.46,
        2406.04,
        3152.63,
        714.87,
        1496.05,
        2323.01,
        3148.32,
        768.71,
        1602.79,
        2451.92,
        3285.82,
        771.69,
        1641.3000000000002,
        2518.69,
        3367.57
      ],
      "Cost of Revenue": [
        628.9,
        1273.87,
        1942.6999999999998,
        2601.1299999999997,
        605.66,
        1242.57,
        1888.73,
        2542.63,
        609.79,
        1234.67,
        1879.3200000000002,
        2503.4,
        635.99,
        1270.9099999999999,
        1911.5899999999997,
        2538.0699999999997,
        661.71,
        1317.18,
        1973.77,
        2617.0699999999997,
        641.64,
        1309.75,
        2003.0,
        2680.59,
        659.83,
        1349.75,
        2045.55,
        2735.43,
        656.97,
        1369.4,
        2086.82,
        2796.2000000000003
      ],
      "Gross Profit": [
        39.37,
        128.23,
        201.45,
        249.77999999999997,
        49.2,
        135.66,
        233.64,
        336.19,
        51.8,
        126.11999999999999,
        228.35,
        327.1,
        82.48,
        220.36,
        376.44000000000005,
        546.07,
        117.94,
        297.28999999999996,
        432.26,
        535.56,
        73.23,
        186.3,
        320.01,
        467.72,
        108.88,
        253.04,
        406.38,
        550.39,
        114.72,
        271.9,
        431.87,
        571.38
      ],
      "Gross Margin (%)": [
        5.891419507377368,
        9.145567363240852,
        9.395331483338387,
        8.761413022508602,
        7.5129414998396635,
        9.843059576413225,
        11.008499971729583,
        11.678048644930907,
        7.8296225759155975,
        9.268145709477583,
        10.834290160652097,
        11.556302972276887,
        11.479950450262363,
        14.776666867837482,
        16.45258147838971,
        17.70574617235275,
        15.127300711857886,
        18.414206607782166,
        17.965619856693987,
        16.987721362798677,
        10.243820554786186,
        12.452792353196752,
        13.775661749196082,
        14.856177262794127,
        14.163989020566921,
        15.787470598144484,
        16.57395021044732,
        16.750461072122025,
        14.86607316409439,
        16.566136599037346,
        17.146611929217173,
        16.96713060159106
      ],
      "Selling & Marketing Exp": [
        17.429,
        33.899,
        53.876000000000005,
        124.35000000000001,
        17.76,
        35.503,
        55.748999999999995,
        130.23399999999998,
        17.487,
        40.117999999999995,
        60.41199999999999,
        140.36599999999999,
        20.748,
        40.381,
        63.391999999999996,
        150.362,
        22.872,
        44.082,
        67.111,
        89.111,
        24.944,
        50.442,
        78.111,
        104.261,
        24.375,
        49.503,
        76.425,
        101.763,
        27.667,
        55.854,
        85.793,
        112.414
      ],
      "R&D Exp": [
        null,
        null,
        null,
        null,
        null,
        null,
        null,
        null,
        null,
        null,
        null,
        null,
        null,
        null,
        null,
        null,
        null,
        null,
        null,
        null,
        null,
        null,
        null,
        null,
        null,
        null,
        null,
        0.0,
        0.0,
        0.0,
        0.0,
        0.0
      ],
      "General & Admin Exp": [
        32.42,
        67.66,
        106.25,
        141.28,
        36.57,
        70.27000000000001,
        108.94000000000001,
        150.51000000000002,
        33.61,
        72.68,
        110.98,
        149.29000000000002,
        44.07,
        90.28,
        139.66,
        194.24,
        50.11,
        101.87,
        148.86,
        190.62,
        47.82,
        93.12,
        146.35,
        198.6,
        48.58,
        101.07,
        158.07,
        209.31,
        52.34,
        107.16,
        165.7,
        220.76
      ],
      "Operating Income": [
        6.95,
        60.580000000000005,
        95.19,
        108.50999999999999,
        12.63,
        65.39,
        124.7,
        185.68,
        18.2,
        53.44,
        117.36,
        177.81,
        38.41,
        130.07999999999998,
        236.77999999999997,
        351.83,
        67.83,
        195.41,
        283.4,
        344.94,
        25.41,
        93.17999999999999,
        173.66,
        269.12,
        60.3,
        151.97,
        248.31,
        341.07,
        62.39,
        164.74,
        266.17,
        350.62
      ],
      "Operating Margin (%)": [
        1.0400143656660583,
        4.320661864346338,
        4.439521488701817,
        3.806153123037907,
        1.9286270557515233,
        4.744491122671833,
        5.875534782035093,
        6.449864875191919,
        2.7509484726189934,
        3.927130563863638,
        5.568260535380469,
        6.281951181597534,
        5.3460826478489,
        8.722766501036029,
        10.348640533559438,
        11.40771819696901,
        8.700057718206889,
        12.103737472591455,
        11.778690296088177,
        10.941341039068968,
        3.5544924251961896,
        6.228401457170548,
        7.4756458215849255,
        8.548051024038216,
        7.844310598275031,
        9.481591474865702,
        10.1271656497765,
        10.38005733728567,
        8.084852725835503,
        10.037165661365991,
        10.56779516335873,
        10.411661821432071
      ],
      "Net Income": [
        -3.13,
        35.239999999999995,
        54.839999999999996,
        58.47,
        -23.28,
        -9.030000000000001,
        13.879999999999999,
        35.379999999999995,
        -16.76,
        -28.82,
        5.009999999999998,
        30.749999999999996,
        3.97,
        54.48,
        115.43,
        222.49,
        28.79,
        97.35,
        118.0,
        143.52,
        -31.03,
        8.71,
        47.45,
        97.65,
        20.58,
        67.1,
        116.35999999999999,
        115.54999999999998,
        31.97,
        67.46000000000001,
        116.60000000000001,
        157.09
      ],
      "Net Margin (%)": [
        -0.4683805704366563,
        2.513372797945938,
        2.5576568803488566,
        2.050924090904308,
        -3.5549040267534013,
        -0.655188176138961,
        0.6539889556908347,
        1.228975760902036,
        -2.5332910110491396,
        -2.117887403640532,
        0.2377043735706897,
        1.0863843362809973,
        0.5525630854454605,
        3.653261984751252,
        5.044951333680067,
        7.214004552322528,
        3.6926826139934588,
        6.02987995986274,
        4.904324117637279,
        4.552389592181766,
        -4.340649348832655,
        0.5821997927876743,
        2.0426085122319746,
        3.1016542155816436,
        2.6772124728441153,
        4.1864498780251935,
        4.745668700446996,
        3.516625986816076,
        4.14285529163265,
        4.110156583196247,
        4.629390675311373,
        4.664787962833734
      ],
      "EPS": [
        -0.03,
        0.31999999999999995,
        0.49999999999999994,
        0.5299999999999999,
        -0.19,
        -0.07,
        0.10999999999999999,
        0.27,
        -0.12,
        -0.21,
        0.04000000000000001,
        0.23,
        0.03,
        0.4,
        0.8500000000000001,
        1.6300000000000001,
        0.21,
        0.71,
        0.86,
        1.05,
        -0.23,
        0.05999999999999997,
        0.35,
        0.71,
        0.15,
        0.49,
        0.85,
        0.84,
        0.23,
        0.49,
        0.85,
        1.14
      ],
      "Op Cash Flow": [
        -3.99,
        11.459999999999999,
        126.17999999999999,
        256.9,
        51.51,
        153.59,
        355.78999999999996,
        557.29,
        110.24,
        296.33,
        457.78999999999996,
        726.53,
        125.72,
        315.57,
        442.78999999999996,
        746.72,
        181.74,
        395.31,
        636.85,
        916.6800000000001,
        140.29,
        300.78,
        499.65999999999997,
        772.91,
        160.22,
        368.56,
        615.97,
        837.35,
        234.08,
        425.26,
        646.01,
        878.65
      ],
      "Investing Cash Flow": [
        -18.14,
        -221.60000000000002,
        -304.20000000000005,
        -403.08000000000004,
        -126.69,
        -167.51,
        -189.5,
        -298.56,
        -18.71,
        -97.05000000000001,
        -231.85000000000002,
        -4.700000000000017,
        26.06,
        20.549999999999997,
        -75.52,
        -128.98,
        -7.92,
        -108.47,
        -155.85,
        -210.41,
        -20.73,
        -246.35999999999999,
        -318.83,
        -339.40999999999997,
        -81.38,
        -101.84,
        -102.5,
        -8.36,
        -137.91,
        -349.97,
        -425.73,
        -1059.1100000000001
      ],
      "Financing Cash Flow": [
        34.51,
        172.37,
        178.93,
        141.74,
        163.87,
        175.59,
        -16.659999999999997,
        -164.6,
        -118.96,
        -245.51999999999998,
        -237.24999999999997,
        -567.5,
        -157.42,
        -342.96,
        -367.79999999999995,
        -548.4699999999999,
        -41.58,
        -286.99,
        -476.40999999999997,
        -650.03,
        -108.45,
        -116.18,
        -230.0,
        -399.05,
        -151.75,
        -363.12,
        -543.45,
        -783.87,
        -110.16,
        -190.42000000000002,
        -292.86,
        145.71999999999997
      ],
      "CAPEX": [
        -52.853,
        -152.778,
        -499.73900000000003,
        -896.288,
        -52.853,
        -152.778,
        -499.73900000000003,
        -896.288,
        -51.818,
        -148.017,
        -263.58299999999997,
        -386.597,
        -16.344,
        -67.86,
        -133.015,
        -253.84499999999997,
        -13.136,
        -59.163,
        -125.011,
        -252.863,
        -19.797,
        -137.07500000000002,
        -255.579,
        -416.37,
        -19.797,
        -137.07500000000002,
        -255.579,
        -416.37,
        -23.185,
        -61.364999999999995,
        -121.892,
        -567.037
      ]
    }
  },
  "listingStatus": "listed",
  "exchange": "TWSE"
}