{
  "ticker": "3285",
  "updatedAt": "2026-04-07T18:17:19Z",
  "unit": "Million NTD; margin rows are percent",
  "valuation": {
    "P/E (TTM)": 40.64,
    "Forward P/E": null,
    "P/S (TTM)": 1.77,
    "P/B": 2.09,
    "EV/EBITDA": 44.4,
    "ROE": 6.03,
    "Beta": 0.26,
    "Debt/Equity": 1.29
  },
  "annual": {
    "periods": [
      "2022-12-31",
      "2023-12-31",
      "2024-12-31",
      "2025-12-31"
    ],
    "series": {
      "Revenue": [
        857.832,
        745.37,
        844.662,
        678.576
      ],
      "Gross Profit": [
        130.84,
        178.516,
        188.553,
        167.403
      ],
      "Gross Margin (%)": [
        15.25240373406448,
        23.949984571420906,
        22.322893654503222,
        24.669749593265898
      ],
      "Selling & Marketing Exp": [
        72.785,
        71.956,
        70.101,
        65.256
      ],
      "R&D Exp": [
        18.517,
        15.43,
        13.528,
        11.684
      ],
      "General & Admin Exp": [
        64.76,
        64.359,
        73.553,
        67.752
      ],
      "Operating Income": [
        -25.222,
        26.771,
        31.371,
        22.711
      ],
      "Operating Margin (%)": [
        -2.9402027436607634,
        3.591639051746113,
        3.714029990694503,
        3.3468616632477426
      ],
      "Net Income": [
        -19.828,
        28.029,
        50.246,
        29.986
      ],
      "Net Margin (%)": [
        -2.311408294397971,
        3.7604142908890887,
        5.948651650009116,
        4.418959703850416
      ],
      "Op Cash Flow": [
        77.102,
        118.051,
        51.483,
        43.982
      ],
      "Investing Cash Flow": [
        -9.499,
        -45.547,
        42.917,
        36.359
      ],
      "Financing Cash Flow": [
        -34.635,
        -99.637,
        -57.922,
        -53.595
      ],
      "CAPEX": [
        -34.724,
        -1.15,
        -2.784,
        -1.47
      ]
    }
  },
  "quarterly": {
    "periods": [
      "2024-09-30",
      "2024-12-31",
      "2025-03-31",
      "2025-06-30",
      "2025-09-30",
      "2025-12-31"
    ],
    "series": {
      "Revenue": [
        null,
        208.184,
        138.659,
        167.56,
        173.207,
        199.15
      ],
      "Gross Profit": [
        null,
        45.503,
        28.148,
        33.155,
        49.122,
        56.978
      ],
      "Gross Margin (%)": [
        null,
        21.857107174422627,
        20.300160826199527,
        19.78694199092862,
        28.36028566974776,
        28.61059502887271
      ],
      "Selling & Marketing Exp": [
        null,
        17.425,
        13.946,
        17.288,
        17.196,
        16.826
      ],
      "R&D Exp": [
        null,
        2.998,
        2.815,
        2.768,
        3.005,
        3.096
      ],
      "General & Admin Exp": [
        null,
        20.063,
        15.504,
        15.191,
        17.632,
        19.425
      ],
      "Operating Income": [
        null,
        5.017,
        -4.117,
        -2.092,
        11.289,
        17.631
      ],
      "Operating Margin (%)": [
        null,
        2.409887407293548,
        -2.9691545446022256,
        -1.2485079971353545,
        6.517634968563627,
        8.853125784584485
      ],
      "Net Income": [
        null,
        19.104,
        0.794,
        -10.505,
        23.572,
        16.125
      ],
      "Net Margin (%)": [
        null,
        9.176497713561082,
        0.5726278135569995,
        -6.269396037240392,
        13.609149745680025,
        8.09691187547075
      ],
      "Op Cash Flow": [
        null,
        15.826,
        23.52,
        -17.148,
        1.806,
        35.804
      ],
      "Investing Cash Flow": [
        null,
        -28.933,
        0.326,
        33.239,
        -0.205,
        2.999
      ],
      "Financing Cash Flow": [
        null,
        -4.683,
        -2.177,
        -2.044,
        -47.247,
        -2.127
      ],
      "CAPEX": [
        -0.161,
        -1.313,
        -0.012,
        -0.637,
        -0.195,
        -0.691
      ]
    }
  },
  "quarterlyCore": {
    "periods": [
      "2024-09-30",
      "2024-12-31",
      "2025-03-31",
      "2025-06-30",
      "2025-09-30",
      "2025-12-31"
    ],
    "series": {
      "Revenue": [
        null,
        208.184,
        138.659,
        167.56,
        173.207,
        199.15
      ],
      "Gross Profit": [
        null,
        45.503,
        28.148,
        33.155,
        49.122,
        56.978
      ],
      "Gross Margin (%)": [
        null,
        21.857107174422627,
        20.300160826199527,
        19.78694199092862,
        28.36028566974776,
        28.61059502887271
      ],
      "Selling & Marketing Exp": [
        null,
        17.425,
        13.946,
        17.288,
        17.196,
        16.826
      ],
      "R&D Exp": [
        null,
        2.998,
        2.815,
        2.768,
        3.005,
        3.096
      ],
      "General & Admin Exp": [
        null,
        20.063,
        15.504,
        15.191,
        17.632,
        19.425
      ],
      "Operating Income": [
        null,
        5.017,
        -4.117,
        -2.092,
        11.289,
        17.631
      ],
      "Operating Margin (%)": [
        null,
        2.409887407293548,
        -2.9691545446022256,
        -1.2485079971353545,
        6.517634968563627,
        8.853125784584485
      ],
      "Net Income": [
        null,
        19.104,
        0.794,
        -10.505,
        23.572,
        16.125
      ],
      "Net Margin (%)": [
        null,
        9.176497713561082,
        0.5726278135569995,
        -6.269396037240392,
        13.609149745680025,
        8.09691187547075
      ],
      "Op Cash Flow": [
        null,
        15.826,
        23.52,
        -17.148,
        1.806,
        35.804
      ],
      "Investing Cash Flow": [
        null,
        -28.933,
        0.326,
        33.239,
        -0.205,
        2.999
      ],
      "Financing Cash Flow": [
        null,
        -4.683,
        -2.177,
        -2.044,
        -47.247,
        -2.127
      ],
      "CAPEX": [
        -0.161,
        -1.313,
        -0.012,
        -0.637,
        -0.195,
        -0.691
      ]
    }
  }
}